mdrunner/__init__.py
mdrunner/model.py
mdrunner/model_input.py
mdrunner/model_interface.py
mdrunner/model_output.py
mdrunner/model_protected.py
mdrunner/model_selector.py
mdrunner/runner.py
mdrunner/runner_protected.py
mdrunner-0.0.5.dist-info/METADATA
mdrunner-0.0.5.dist-info/WHEEL
mdrunner-0.0.5.dist-info/licenses/LICENSE
mdrunner-0.0.5.dist-info/RECORD
