Metadata-Version: 2.1
Name: mdrunner
Version: 0.0.5
Summary: A framework for running user-defined calculations (here called models)
Project-URL: Homepage, https://github.com/PeterKanderholm/mdrunner
Project-URL: Bug Tracker, https://github.com/PeterKanderholm/mdrunner/issues
Author-email: Peter Kanderholm <peter.kanderholm@gmail.com>
License: MIT License
License-File: LICENSE
Classifier: Intended Audience :: Developers
Classifier: License :: OSI Approved :: MIT License
Classifier: Operating System :: OS Independent
Classifier: Programming Language :: Python
Classifier: Programming Language :: Python :: 3
Classifier: Programming Language :: Python :: 3.7
Classifier: Programming Language :: Python :: 3.8
Classifier: Programming Language :: Python :: 3.9
Classifier: Programming Language :: Python :: 3.10
Classifier: Programming Language :: Python :: 3.11
Classifier: Programming Language :: Python :: 3.12
Requires-Python: >=3.7
